{
    "title": "V2.2.1\\Emsp\\Server\\Locations\\Put",
    "oneOf": [
        {
            "$ref": "../../../Common/Locations/location.schema.json",
            "required": [
                "country_code",
                "party_id",
                "id",
                "publish",
                "address",
                "city",
                "country",
                "coordinates",
                "time_zone",
                "last_updated"
            ],
            "additionalProperties": false
        }
    ]
}
